.gitignore
CHANGES.txt
README.rst
setup.cfg
setup.py
metafanstatic/__init__.py
metafanstatic/cache.py
metafanstatic/classifier.py
metafanstatic/command.py
metafanstatic/compat.py
metafanstatic/complement.py
metafanstatic/control.py
metafanstatic/decorator.py
metafanstatic/dependency.py
metafanstatic/detector.py
metafanstatic/downloading.py
metafanstatic/generating.py
metafanstatic/information.py
metafanstatic/interfaces.py
metafanstatic/loading.py
metafanstatic/viewhelpers.py
metafanstatic.egg-info/PKG-INFO
metafanstatic.egg-info/SOURCES.txt
metafanstatic.egg-info/dependency_links.txt
metafanstatic.egg-info/entry_points.txt
metafanstatic.egg-info/not-zip-safe
metafanstatic.egg-info/requires.txt
metafanstatic.egg-info/top_level.txt
metafanstatic/scaffolds/__init__.py
metafanstatic/tests/__init__.py
metafanstatic/tests/test_complement.py
metafanstatic/tests/test_it.py
metafanstatic/tests/test_loader.py