Metadata-Version: 1.1
Name: metafanstatic
Version: 0.1.1
Summary: generate fanstatic package
Home-page: https://github.com/podhmo/metafanstatic
Author: UNKNOWN
Author-email: UNKNOWN
License: UNKNOWN
Platform: UNKNOWN
Classifier: Programming Language :: Python
Classifier: Programming Language :: Python :: Implementation :: CPython
